LICENSE
MANIFEST.in
README.md
install.json
package.json
pyproject.toml
setup.py
tsconfig.json
yarn.lock
jupyter-config/jupyterlab_dosbox.json
jupyterlab_dosbox/__init__.py
jupyterlab_dosbox/_version.py
jupyterlab_dosbox/dosbox_view.py
jupyterlab_dosbox/handlers.py
jupyterlab_dosbox/utils.py
jupyterlab_dosbox.egg-info/PKG-INFO
jupyterlab_dosbox.egg-info/SOURCES.txt
jupyterlab_dosbox.egg-info/dependency_links.txt
jupyterlab_dosbox.egg-info/not-zip-safe
jupyterlab_dosbox.egg-info/requires.txt
jupyterlab_dosbox.egg-info/top_level.txt
jupyterlab_dosbox/bundles/637915aacd582e7603a0071d42348135-wdirect.wasm
jupyterlab_dosbox/bundles/65032eda83f0536cf4a1d9e13be2747e-wdirect.js
jupyterlab_dosbox/bundles/dosbox.conf
jupyterlab_dosbox/bundles/jsdos.json
jupyterlab_dosbox/labextension/package.json
jupyterlab_dosbox/labextension/static/248.8ae1729bf7a4097ce32a.js
jupyterlab_dosbox/labextension/static/480.8ad5b27fdf7d4bb332a8.js
jupyterlab_dosbox/labextension/static/514.531f915e4ca72a4f2b63.js
jupyterlab_dosbox/labextension/static/534.afeac957d69a14688ca1.js
jupyterlab_dosbox/labextension/static/534.afeac957d69a14688ca1.js.LICENSE.txt
jupyterlab_dosbox/labextension/static/553.85d42beb489c3bb87c8b.js
jupyterlab_dosbox/labextension/static/568.afe698483255c79b5066.js
jupyterlab_dosbox/labextension/static/776.46f960e7706a4e233b38.js
jupyterlab_dosbox/labextension/static/remoteEntry.43866abe6695b30cf042.js
jupyterlab_dosbox/labextension/static/style.js
src/contents.ts
src/index.ts
src/layerinterface.ts
src/plugin.ts
src/standalone.ts
src/version.ts
src/widget.ts
style/base.css
style/index.css
style/index.js